{
    "dia": {
        "tirante_inicio": 2.21,
        "tirante_fin": 2.68,
        "volumen_inicio": 3689.0,
        "volumen_fin": 4463.0,
        "volumen_rebombeado": 774.0,
        "horas_operacion": 1.6,
        "gasto_lps": 134.4,
        "alertas": []
    },
    "noche": {
        "tirante_inicio": 1.86,
        "tirante_fin": 2.95,
        "volumen_inicio": 3093.0,
        "volumen_fin": 4911.0,
        "volumen_rebombeado": 1818.0,
        "horas_operacion": 10.6,
        "gasto_lps": 47.4,
        "alertas": []
    }
}